{
    "返回": "Retour",
    "新增班课": "Nouvelle classe",
    "保存": "Enregistrer",
    "保存中": "Enregistrer",
    "退出": "Sortie",
    "登录": "Connexion",
    "信息": "Information",
    "服务开小差": "Écart de service",
    "班课名": "Nom de la classe",
    "班课封面": "Couverture de classe",
    "请输入班课": "Veuillez entrer la classe",
    "班课": "Classe",
    "未知班课": "Classe inconnue",
    "我的": "La mienne.",
    "当前没有文件": "Il n'y a actuellement aucun fichier",
    "请输入": "Veuillez entrer",
    "标题": "Titre",
    "链接": "Liens",
    "签到": "Inscrivez - vous.",
    "人": "Les gens",
    "总数": "Total général",
    "点击": "Cliquez sur",
    "加载中": "Chargement en cours",
    "尽请期待": "Attendez.",
    "添加": "Ajouter",
    "提交": "Présentation",
    "下拉刷新全部": "Rafraîchir tout dans la liste déroulante",
    "上拉加载更多": "Charger plus",
    "结束": "Fin",
    "删除": "Supprimer",
    "开始": "C'est parti.",
    "编辑": "Édition",
    "教师": "Enseignants",
    "学员": "Stagiaires",
    "游客": "Touristes",
    "前": "Avant",
    "月": "Mois",
    "天": "Oh, mon Dieu.",
    "小时": "Heures",
    "分": "Points",
    "秒": "Secondes",
    "全部": "Tous",
    "关闭": "Fermer",
    "从本地上传": "Téléchargement local",
    "网页链接": "Liens vers les pages Web",
    "资源库": "Base de ressources",
    "资源": "Ressources",
    "成员": "Membres",
    "作业": "Opérations",
    "互动": "Interaction",
    "详情": "Détails",
    "小组方案": "Programme du Groupe",
    "没有任何作业": "Pas de travail",
    "新增 作业": "Nouvel emploi",
    "进行中": "En cours",
    "已结束": "Terminé.",
    "未开始": "Non commencé",
    "已参与": "Participation",
    "未参与": "Pas de participation",
    "参与": "Participation",
    "作业结果列表": "Liste des résultats des travaux",
    "作业详细": "Détails de l'emploi",
    "提交作业": "Soumettre un emploi",
    "作业分值": "Score d'emploi",
    "本次作业所有人得分": "Score du propriétaire de l'opération",
    "答案": "La réponse",
    "我的提交": "Ma soumission",
    "未评分": "Non évalué",
    "尚未提交": "Non encore soumis",
    "来提交": "Pour soumettre",
    "已提交": "Soumis",
    "评论区": "Zone de commentaires",
    "给": "Voilà.",
    "评分": "Notation",
    "总体评分": "Note globale",
    "满分": "Score complet",
    "作业答案": "Réponses aux devoirs",
    "所有提交": "Toutes les soumissions",
    "未设置答案": "Aucune réponse définie",
    "尚无未评分": "Pas encore non évalué",
    "尚无提交": "Pas encore soumis",
    "不限制提交时间": "Aucun délai de soumission",
    "允许超时提交": "Autoriser les délais de soumission",
    "不允许超时提交": "Délai de soumission non autorisé",
    "无学员参与": "Aucun participant",
    "已全部提交": "Tous soumis",
    "未提交": "Non soumis",
    "附件": "Annexe",
    "输入详细内容": "Entrer les détails",
    "添加附件(%sM以内)": "Ajouter des accessoires (moins de %sm)",
    "添加附件": "Ajouter une pièce jointe",
    "等待上传": "En attente de téléchargement",
    "视频": "Vidéo",
    "上传失败": "Impossible de télécharger",
    "删除文件": "Supprimer le fichier",
    "活动尚未结束，以下得分可能不是最终得分": "L'activité n'est pas terminée et les points suivants peuvent ne pas être définitifs",
    "创建时间": "Temps de création",
    "最后一次开始时间": "Dernière heure de début",
    "首次提交": "Première communication",
    "未提交作业": "Aucun emploi soumis",
    "签到时间": "Heure d'inscription",
    "结束时间": "Fin",
    "查看所有签到记录": "Voir tous les enregistrements d'enregistrement",
    "所有签到记录": "Tous les enregistrements d'enregistrement",
    "暂无签到记录": "Pas de registre d'inscription pour le moment",
    "暂无学生签到记录": "Pas de registre d'inscription des étudiants",
    "所有学生签到记录": "Registre d'inscription de tous les élèves",
    "下课": "La classe est finie.",
    "已下课": "La classe est finie.",
    "当前未开课": "Aucun cours n'est actuellement ouvert",
    "当前已开课": "Cours en cours",
    "当前已下课": "Cours en cours",
    "签到成功": "Inscription réussie",
    "你迟到了哦": "Tu es en retard.",
    "已经过了签到时间了": "Il est temps de s'inscrire.",
    "当前无课": "Pas de cours en cours",
    "已签到": "Signé",
    "未签到": "Non signé",
    "迟到": "En retard.",
    "超时": "Temps mort",
    "编辑班课": "Modifier la classe",
    "结束班课": "Fin de la classe",
    "删除班课": "Supprimer la classe",
    "账户": "Comptes",
    "设置": "Paramètres",
    "关于": "À propos de",
    "个人信息": "Renseignements personnels",
    "头像": "Portrait",
    "昵称": "Un surnom.",
    "角色": "Rôle",
    "编辑头像": "Modifier le portrait",
    "填写您的个人昵称": "Remplissez votre surnom personnel",
    "设置您的个人昵称": "Définir votre surnom personnel",
    "上传中": "Téléchargement en cours",
    "处理中": "En cours de traitement",
    "提交中": "En attente",
    "登录中": "Connexion en cours",
    "创建中": "En cours de création",
    "提示": "Conseils",
    "确认": "Confirmation",
    "取消": "Annulation",
    "操作成功": "Opération réussie",
    "您确定要退出当前账户吗": "Êtes - vous sûr de vouloir quitter le compte courant",
    "语言": "Langues",
    "连接失败,点击重连": "La connexion a échoué, cliquez sur reconnecter",
    "多屏": "Écran multiple",
    "确定": "C'est sûr.",
    "允许学生加入": "Permettre aux étudiants d'adhérer",
    "允许学生退课": "Permettre aux étudiants de quitter le cours",
    "你有未保存的修改,是否退出": "Vous avez des modifications non enregistrées, voulez - vous quitter",
    "你确定要修改吗": "Tu es sûr de vouloir le modifier?",
    "设置成功": "Configuration réussie",
    "班级": "Classe",
    "班级名": "Nom de la classe",
    "成功": "Succès",
    "失败": "Échec",
    "班课号": "Numéro de classe",
    "所属学校": "École",
    "发布公告": "Publier un avis",
    "班级设置": "Configuration de la classe",
    "得分占比设置": "Paramètres du rapport de notation",
    "学情统计": "Statistiques de l'apprentissage",
    "分享班课": "Cours de partage",
    "查看公告": "Voir les annonces",
    "查看得分占比": "Voir le pourcentage de points",
    "退出班课": "Quitter la classe",
    "得分占比": "Pourcentage de points",
    "未绑定过学校": "Non lié à l'école",
    "未找到数据": "Aucune donnée trouvée",
    "归档后,只能查阅,不可再开始该班课,是否继续": "Après le dépôt, il ne peut être consulté qu'au lieu de commencer la classe. Voulez - vous continuer?",
    "禁止退出班课": "Interdiction de quitter la classe",
    "服务出错了": "Erreur de service",
    "确认退出": "Confirmer la sortie",
    "请再次确认是否要退出当前班课,退出当前班课后,提交的作业及得分等数据将会清空,无法恢复,请谨慎操作": "Veuillez confirmer à nouveau si vous souhaitez quitter la classe actuelle. Après la sortie de la classe actuelle, les données telles que les devoirs soumis et les scores seront effacées et ne peuvent pas être récupérées. Veuillez faire preuve de prudence.",
    "退出并清除数据": "Quitter et effacer les données",
    "退出成功": "Sortie réussie",
    "请输入公告内容": "Veuillez entrer le contenu de l'annonce",
    "暂无公告": "Aucune annonce",
    "发布": "Publication",
    "请输入公告": "Veuillez entrer l'annonce",
    "发布成功": "Publié avec succès",
    "设置各类教学活动在学生得分中的占比": "Définir la proportion de toutes sortes d'activités d'enseignement dans les scores des élèves",
    "资源得分占比": "Part des ressources",
    "签到得分占比": "Pourcentage de points d'inscription",
    "作业得分占比": "Pourcentage de notes de travail",
    "评测得分占比": "Proportion des notes d'évaluation",
    "恢复默认": "Restaurer par défaut",
    "异常": "Anomalie",
    "正在上课": "Cours en cours",
    "班级号": "Numéro de classe",
    "公告": "Annonces",
    "已经加载全部了": "Tout est chargé.",
    "课程管理": "Gestion des cours",
    "归档课程": "Cours d'archivage",
    "课程归档后无法发布资源,创建作业等,但仍可以查看已发布的资源,已结束的作业等": "Impossible de publier les ressources, de créer des emplois, etc., après l'archivage du cours, mais vous pouvez toujours voir les ressources publiées, les emplois terminés, etc.",
    "创建班级": "Créer une classe",
    "创建": "Création",
    "请输入班级名称": "Veuillez saisir le nom de la classe",
    "课程资源": "Ressources pédagogiques",
    "统计": "Statistiques",
    "课程": "Cours",
    "确定要归档吗": "Tu es sûr de vouloir l'archiver?",
    "归档后": "Après le dépôt",
    "不可再开始该课程": "Ne recommencez pas le cours.",
    "操作失败": "L'opération a échoué",
    "无权限": "Aucune autorisation",
    "超出数量限制": "Dépassement de la limite de quantité",
    "功能已被禁用": "Fonction désactivée",
    "学校班课数已达上限": "Le nombre de classes a atteint la limite supérieure",
    "您创建的班课数已达上限": "Vous avez créé le nombre maximum de classes",
    "请先结束部分班课": "Veuillez terminer la classe.",
    "未创建班级": "Classe non créée",
    "教案": "Plan d'enseignement",
    "发布任务": "Publier la tâche",
    "加入班课": "Rejoindre la classe",
    "请输入班课号": "Veuillez saisir le numéro de classe",
    "下一步": "Prochaines étapes",
    "错误": "Erreur",
    "禁止加入班课": "Pas de classe",
    "未找到班课": "Classe introuvable",
    "服务异常": "Service anormal",
    "我的任务": "Ma mission",
    "收藏": "Collection",
    "您确定要删除吗": "Êtes - vous sûr de vouloir supprimer",
    "删除成功": "Suppression réussie",
    "结束作业": "Fin du travail",
    "结束后学生不可再提交": "Les étudiants ne peuvent plus soumettre après la fin",
    "结束讨论": "Clôture de la discussion",
    "结束后将不可再提交": "Ne pas soumettre après la fin",
    "试卷编辑": "Édition des documents d'examen",
    "题库编辑": "Édition de la Banque de questions",
    "视听语言训练": "Formation linguistique audiovisuelle",
    "我的教学": "Mon enseignement",
    "学生录音": "Enregistrement des élèves",
    "我的录音": "Mon enregistrement",
    "最多同时上传": "Téléchargement simultané maximum",
    "个文件": "Fichiers",
    "原文件": "Documents originaux",
    "此文件大小超过上限,建议小于%s": "La taille de ce fichier dépasse la limite supérieure, moins de %s est recommandé",
    "请在新版": "S'il vous plaît dans la nouvelle édition",
    "中查看": "Vue moyenne",
    "未设置服务器": "Serveur non défini",
    "服务开小差了": "Le service était médiocre.",
    "请在PC浏览器中打开": "Veuillez ouvrir dans le navigateur PC",
    "加入": "Adhésion",
    "加入失败": "Échec de l'adhésion",
    "班课人数已达上限": "Nombre maximum de classes",
    "班课已结束": "La classe est terminée.",
    "不能加入自己的班课": "Je ne peux pas rejoindre ma classe.",
    "已在班课中": "Déjà en classe",
    "返回上一层": "Retour au niveau précédent",
    "未找到文件": "Fichier introuvable",
    "训练": "Formation",
    "未关联字幕文件,请先关联": "Aucun fichier de sous - titres associé, veuillez d'abord associer",
    "课堂板书": "Livre de classe",
    "请选择一个或多个班课进行合班教学": "Veuillez sélectionner une ou plusieurs classes pour l'enseignement combiné",
    "至少选择一个自己的班课": "Choisissez au moins une de vos propres classes",
    "当前合班班课": "Classe actuelle",
    "查看更多": "Voir plus",
    "收起": "Range ça.",
    "开始上课": "Commencez le cours.",
    "已登录到大屏": "Connecté au grand écran",
    "下课后请及时退出大屏登录": "Veuillez quitter le grand écran après la classe",
    "我知道了": "Je le vois.",
    "退出大屏": "Quitter le grand écran",
    "自己班课": "Cours en classe",
    "学校班课": "Classes scolaires",
    "合班教学-选择班课": "Enseignement en classe - sélection des classes",
    "登录确认": "Confirmation de connexion",
    "已登录": "Connecté",
    "大屏登录": "Connexion grand écran",
    "请求数据失败": "Échec de la demande de données",
    "当前班课无效,请返回重试": "La classe actuelle n'est pas valide. Veuillez réessayer.",
    "登录成功": "Connexion réussie",
    "登录错误": "Erreur de connexion",
    "大屏查询": "Requête grand écran",
    "您确定要退出大屏吗": "Êtes - vous sûr de vouloir quitter le grand écran",
    "退出失败": "Échec de la sortie",
    "请输入大屏上的连接码进行登录": "Veuillez entrer le Code de connexion sur le grand écran pour vous connecter",
    "连接大屏后自动开始签到": "L'inscription commence automatiquement après la connexion au grand écran",
    "弹幕互动": "Interaction du rideau",
    "无数据": "Aucune donnée disponible",
    "请输入弹幕内容": "Veuillez saisir le contenu du rideau",
    "发送": "Envoyer",
    "弹幕颜色": "Couleur du rideau",
    "橙色": "Orange",
    "红色": "Rouge",
    "蓝色": "Bleu",
    "紫色": "Violet",
    "绿色": "Vert",
    "粉色": "Rose",
    "查询失败": "La requête a échoué",
    "最大可输入24个字符": "Jusqu'à 24 caractères peuvent être saisis",
    "当前班课未开课": "La classe actuelle n'est pas ouverte",
    "发送中": "Envoi en cours",
    "发送成功": "Envoyé avec succès",
    "发送失败": "Échec de l'envoi",
    "前天": "La veille.",
    "昨天": "Hier.",
    "今天": "Aujourd'hui",
    "明天": "Demain.",
    "后天": "Après - demain.",
    "题目": "Titre",
    "无提交": "Aucune soumission",
    "的答案": "La réponse",
    "对": "C'est exact.",
    "错": "Faux.",
    "已作答": "J'ai répondu.",
    "未作答": "Pas de réponse",
    "正确": "Exact.",
    "投票": "Vote",
    "未知用户": "Utilisateur inconnu",
    "提交详细": "Détails de la soumission",
    "连接错误": "Erreur de connexion",
    "评测记录": "Dossiers d'évaluation",
    "选择": "Sélectionner",
    "判断": "Jugement",
    "主观": "Subjectivité",
    "写作": "Écrire",
    "抢答": "Réponse rapide",
    "未找到记录": "Aucun enregistrement trouvé",
    "请选择你支持的答案": "Veuillez sélectionner la réponse que vous soutenez",
    "是的范德萨范德萨": "Oui, van der Sar van der Sar.",
    "请投票": "Votez.",
    "你已提交过": "Vous avez soumis",
    "请选择": "Veuillez sélectionner",
    "请下拉本页面": "Veuillez déposer cette page",
    "刷新": "Rafraîchir",
    "请点击选项作答": "Veuillez cliquer sur options pour répondre",
    "解析错误": "Erreur de résolution",
    "评测": "Évaluation",
    "当前没有评测": "Aucun commentaire actuel",
    "提交成功": "Soumis avec succès",
    "提交失败": "Échec de la soumission",
    "你未提交,确定要离开吗": "Tu es sûr de vouloir partir?",
    "请输入答案后点击提交": "Veuillez entrer la réponse et cliquer sur soumettre",
    "点击抢答": "Cliquez pour répondre",
    "你已抢答过": "Vous avez répondu",
    "请绘制": "Veuillez dessiner",
    "请在云班课小程序中查看": "Voir dans l'applet cours en nuage",
    "个人学情": "Situation personnelle",
    "在本班课中得分": "Marquer dans cette classe",
    "资源得分": "Note relative aux ressources",
    "作业得分": "Score d'affectation",
    "评测得分": "Note d'évaluation",
    "签到得分": "Score d'inscription",
    "学生在本班课中的总得分是按得分占比折算后的得分": "Les notes totales des élèves dans cette classe sont converties en pourcentage des notes.",
    "更新": "Mise à jour",
    "文件夹": "Dossiers",
    "没有文件夹": "Pas de dossier",
    "新建文件夹": "Nouveau dossier",
    "请输入文件名": "Veuillez saisir un nom de fichier",
    "创建失败": "Impossible de créer",
    "服务连接失败": "La connexion de service a échoué",
    "未找到到文件": "Fichier introuvable",
    "中文": "En chinois",
    "公共": "Public",
    "学校": "Écoles",
    "跟读模仿": "Imitation de la lecture",
    "语音实践": "Pratique phonétique",
    "拓展练习": "Exercice d'expansion",
    "语音学习": "Apprentissage phonétique",
    "上传本地文件": "Télécharger des fichiers locaux",
    "添加网页链接": "Ajouter un lien Web",
    "移动": "En mouvement",
    "重命名": "Renommer",
    "设置字幕": "Définir les sous - titres",
    "设置语系": "Définir la famille linguistique",
    "设置多音轨": "Configuration des pistes multiples",
    "请设置字幕文件": "Veuillez définir le fichier de légende",
    "当前文件不支持此功能": "Cette fonctionnalité n'est pas prise en charge dans le fichier courant",
    "仅支持前三项": "Seuls les trois premiers sont pris en charge",
    "仅支持最后一项": "Seul le dernier élément est pris en charge",
    "连接服务失败": "Le Service de connexion a échoué",
    "服务出错": "Erreur de service",
    "稍后再试": "Essaie plus tard.",
    "不能为空": "Ne peut pas être vide",
    "修改中": "En cours de modification",
    "上传资源": "Télécharger les ressources",
    "目录": "Table des matières",
    "选择音轨文件": "Sélectionner un fichier de piste",
    "选择字幕文件": "Sélectionner un fichier de sous - titres",
    "设置失败": "Échec de la configuration",
    "文件格式不对": "Mauvais format de fichier",
    "请上传": "Veuillez télécharger",
    "文件": "Documentation",
    "网址": "Site Web",
    "请填写详细信息": "Veuillez remplir les détails",
    "添加成功": "Ajouté avec succès",
    "请输入答案": "Veuillez entrer la réponse",
    "评论": "Commentaires",
    "老师": "Professeur.",
    "回复": "Réponse",
    "我是有底线的": "J'ai des résultats.",
    "输入你的观点": "Entrez votre point de vue",
    "在此发表评论": "Commentaires ici",
    "好好": "D'accord.",
    "考试结果": "Résultats des examens",
    "阅卷中": "En cours de notation",
    "考试已结束": "L'examen est terminé.",
    "未参加考试": "Pas d'examen",
    "老师正在阅卷": "Le professeur lit les papiers.",
    "你已经收藏过了": "Tu l'as déjà collecté.",
    "未参加": "Non - Participation",
    "考试中": "À l'examen",
    "考试暂停中": "Examen suspendu",
    "已交卷": "Document transmis",
    "已统一交卷": "Volume unifié",
    "已阅卷": "Noté",
    "等待阅卷": "En attente de notation",
    "请稍后查看结果": "Voir les résultats plus tard",
    "发布设置": "Paramètres de publication",
    "发放对象": "Objet de la distribution",
    "全选": "Sélectionner tout",
    "设置最晚提交时间": "Définir la dernière heure de soumission",
    "最晚提交时间": "Dernière soumission",
    "允许超时提交作业": "Autoriser les délais de soumission des emplois",
    "开启允许超时提交作业后,老师评分,和指定助教/学生评分类型的作业,系统将允许超时提交作业,但会标记为超时": "Une fois que vous avez activé le temps d'arrêt autorisé pour soumettre une tâche, l'enseignant classe et spécifie le type de travail pour lequel l'AT / l'élève classe, le système permet le temps d'arrêt pour soumettre une tâche, mais il est marqué comme temps d'arrêt",
    "开启允许超时提交作业后,老师评分,和,指定助教,学生评分": "Après avoir activé le délai de soumission des devoirs, l'enseignant classe, et, assigne un assistant enseignant, l'élève classe",
    "类型的作业": "Type d'emploi",
    "系统将允许超时提交作业": "Le système permettra de temporiser la soumission des emplois",
    "但会标记为超时": "Mais sera marqué comme Timeout",
    "日": "Jour",
    "时": "Heure",
    "发布中": "En cours de publication",
    "查询班级中": "Interrogation en classe",
    "活动尚未结束,以下得分可能不是最终得分": "L'activité n'est pas terminée et les points suivants peuvent ne pas être définitifs",
    "训练得分": "Points d'entraînement",
    "点击继续": "Cliquez pour continuer",
    "完成": "Terminé.",
    "进度": "Progrès accomplis",
    "分值": "Points",
    "其他同学的": "D'autres étudiants",
    "已完成": "Terminé",
    "未完成": "Non terminé",
    "发音训练": "Formation à la prononciation",
    "听写训练": "Formation à la dictée",
    "配音训练": "Formation au doublage",
    "任务已结束": "Mission terminée",
    "操作": "Fonctionnement",
    "得分": "Points",
    "编辑记录": "Modifier l'enregistrement",
    "提交历史": "Historique de la soumission",
    "版本": "Version",
    "打回重做": "Rappeler refaire",
    "分享作业": "Partage des tâches",
    "编辑作业": "Modifier la tâche",
    "作答": "Réponse",
    "结果列表": "Liste des résultats",
    "作业尚未结束": "Le travail n'est pas terminé",
    "不能查看学员的提交": "Impossible de voir les soumissions des délégués",
    "作业已被评分,不能编辑": "Le travail a été noté et ne peut pas être édité",
    "退出作业提交": "Quitter la soumission d'emploi",
    "努力加载数据中": "Effort de chargement des données",
    "作业已被打回": "Le travail a été rappelé",
    "请重做": "S'il te plaît, refais - le.",
    "现在提交作业": "Soumettre l'emploi maintenant",
    "已超时": "Délai écoulé",
    "无法再提交作业": "Impossible de soumettre un autre emploi",
    "请联系老师": "Veuillez contacter votre professeur",
    "人查看": "Vue par les gens",
    "讨论": "Discussion",
    "暂未评论": "Aucun commentaire",
    "的作业": "Le travail de",
    "请输入内容或上传文件": "Veuillez saisir le contenu ou télécharger le fichier",
    "此文件大小超上限": "Cette taille de fichier dépasse la limite supérieure",
    "得分统计": "Statistiques des scores",
    "资源得分情况": "Notation des ressources",
    "暂无数据": "Aucune donnée disponible",
    "签到得分情况": "Notes d'inscription",
    "作业得分情况": "Notes de travail",
    "评测得分情况": "Notes d'évaluation",
    "最高分": "Score maximum",
    "最低分": "Score le plus bas",
    "平均分": "Note moyenne",
    "得分曲线": "Courbe de notation",
    "近7天": "Près de 7 jours",
    "近1月": "Près de janvier",
    "近半年": "Près de six mois",
    "次提交": "Submissions",
    "我的作业": "Mes devoirs.",
    "实际签到": "Inscription effective",
    "应签到": "Doit signer",
    "班课人数": "Nombre de classes",
    "成员名单": "Liste des membres",
    "旁听学生": "Étudiants",
    "请使用微信扫码签到": "Veuillez vous inscrire en utilisant Wechat scan code",
    "开启签到": "Ouverture de l'inscription",
    "学生名单": "Liste des étudiants",
    "未知名": "Inconnu",
    "开启失败": "Impossible d'ouvrir",
    "出错了": "Il y a eu une erreur.",
    "的签到状态": "État d'inscription pour",
    "已绑定的学校": "Écoles liées",
    "暂无内容": "Pas de contenu pour le moment",
    "绑定新学校": "Lier une nouvelle école",
    "工号": "Numéro d'emploi",
    "学号": "Numéro d'étudiant",
    "学校信息": "Information scolaire",
    "我在该学校的信息": "Mon message à l'école",
    "取消绑定该学校": "Débloquer l'école",
    "你确认要取消绑定吗": "Êtes - vous sûr de vouloir débloquer",
    "操作中": "En cours",
    "学校绑定": "Reliure scolaire",
    "选择学校": "Choisir une école",
    "请输入工号或学号": "Veuillez saisir le numéro d'emploi ou le numéro d'étudiant",
    "校验码": "Code de contrôle",
    "请输入校验码": "Veuillez saisir le Code de contrôle",
    "没有则不填": "Non, pas de remplissage.",
    "绑定": "Liaison",
    "输入学校名": "Saisissez le nom de l'école",
    "请选择学校": "Veuillez sélectionner une école",
    "全速绑定中": "Liaison à pleine vitesse",
    "绑定成功": "Liaison réussie",
    "绑定失败": "La liaison a échoué",
    "已绑定到该学校": "Lié à l'école",
    "校验码不匹配": "Décalage entre les codes de contrôle",
    "出错啦": "Une erreur.",
    "加入的班课": "Cours suivis",
    "创建的班课": "Classes créées",
    "在班课中得分": "Marquer en classe",
    "中科卓软云班课": "Zhongkezhuo Soft Cloud class",
    "深圳市中科卓软科技有限公司,版权所有": "Shenzhen zhongkezhuo Soft Technology Co., Ltd. Tous droits réservés",
    "已结束班课": "Classe terminée",
    "我的收藏": "Ma collection",
    "删除收藏": "Supprimer les favoris",
    "刪除中": "Supprimer",
    "欢迎使用": "Bienvenue.",
    "真实姓名": "Nom réel",
    "请输入您的姓名": "Veuillez saisir votre nom",
    "请输入姓名": "Veuillez saisir un nom",
    "方便大家认识你": "Pour que tout le monde te connaisse.",
    "绑定学校": "Lier l'école",
    "可选": "Facultatif",
    "开始使用": "Commencer à utiliser",
    "你可以在": "Vous pouvez",
    "页面中随时修改个人信息": "Modifier les renseignements personnels à tout moment sur la page",
    "你可以在我的页面设置相关选项": "Vous pouvez définir les options sur ma page",
    "成员总数": "Nombre total de membres",
    "成员总数%s人": "Nombre total de membres %s",
    "平均得分": "Note moyenne",
    "成员详情": "Détails des membres",
    "查看": "Voir",
    "你无权限": "Vous n'avez pas le droit.",
    "删除失败": "Échec de la suppression",
    "课前": "Avant la classe",
    "课中": "En classe",
    "课后": "Après les cours",
    "学情": "Situation scolaire",
    "新增": "Nouveau",
    "创建云班课": "Créer une classe Cloud",
    "课程封面": "Couverture du cours",
    "课程名称": "Nom du cours",
    "请输入课程名称": "Veuillez saisir le nom du cours",
    "物理": "Physique",
    "化学": "Chimie",
    "英语": "Anglais",
    "未查看": "Non visualisé",
    "已查看": "Vue",
    "播放次数": "Temps de lecture",
    "按文件名称排序": "Trier par nom de fichier",
    "按时间倒序排序": "Trier par ordre chronologique inverse",
    "从资源库上传": "Télécharger à partir du dépôt",
    "添加精选网站": "Ajouter un site Web sélectionné",
    "查看情况": "Voir la situation",
    "未关联字幕": "Sous - titres non associés",
    "文档": "Documentation",
    "刷新试试": "Rafraîchir.",
    "文件排序": "Tri des fichiers",
    "正全速移动": "Mouvement positif à pleine vitesse",
    "已发布": "Publié",
    "作业库": "Base de travail",
    "创建作业": "Créer un emploi",
    "创建影视配音作业": "Créer une tâche de doublage vidéo",
    "创建听写训练作业": "Créer une tâche de formation à la dictée",
    "创建发音训练作业": "Créer une tâche de formation à la prononciation",
    "新增考试": "Nouveaux examens",
    "新建讨论": "Nouvelle discussion",
    "结束考试": "Fin de l'examen",
    "结束阅卷": "Fin de la notation",
    "我创建的": "Je l'ai créé.",
    "我加入的": "Je l'ai rejoint.",
    "暂无课程": "Pas de cours pour le moment",
    "点击创建课程或加入班级": "Cliquez pour créer un cours ou rejoindre une classe",
    "暂无班级": "Pas de classe pour le moment",
    "点击加入班级": "Cliquez pour rejoindre la classe",
    "云班课": "Classe Cloud",
    "搜索": "Recherche",
    "清除搜索记录": "Effacer les enregistrements de recherche",
    "暂无搜索记录": "Pas d'enregistrement de recherche pour le moment",
    "创建课程": "Créer un cours",
    "加入班级": "Rejoindre la classe",
    "置顶课程": "Cours plafonnés",
    "取消置顶": "Annuler le Haut",
    "我的学习": "Mes études",
    "登陆提示": "Conseils de connexion",
    "您未登陆": "Vous n 'aurez pas adjugé",
    "是否现在登陆": "Connectez - vous maintenant",
    "登陆": "Débarquement",
    "加入课堂": "Rejoignez la classe",
    "暂未实现": "Non réalisé",
    "当前无班课": "Il n'y a pas de classe actuellement",
    "发生异常": "Une exception s'est produite",
    "编辑课程": "Modifier le cours",
    "学校课程数已达上限": "Nombre maximum de programmes scolaires",
    "您创建的课程数已达上限": "Vous avez créé un maximum de cours",
    "请先结束部分课程": "Veuillez terminer une partie du cours.",
    "默认班级": "Classe par défaut",
    "创建默认班课失败": "Impossible de créer la classe par défaut",
    "密码登录": "Mot de passe",
    "用户注册": "Inscription des utilisateurs",
    "输入账户名": "Saisissez le nom du compte",
    "请设置账户名": "Veuillez définir le nom du compte",
    "输入密码": "Saisissez le mot de passe",
    "请设置密码": "Veuillez définir le mot de passe",
    "注册": "Inscription",
    "微信登录": "Connexion Wechat",
    "微信扫码登录": "Connexion par balayage de code Wechat",
    "请使用微信扫一扫完成登录": "Veuillez utiliser Wechat Scan pour compléter la connexion",
    "请填写账号": "Veuillez remplir le numéro de compte",
    "请设置账号": "Veuillez définir le numéro de compte",
    "请填写密码": "Veuillez remplir le mot de passe",
    "正全力注册": "J'essaie de m'inscrire.",
    "账户和密码不正确": "Compte et mot de passe incorrects",
    "未登陆": "Non connecté",
    "点击登陆": "Cliquez pour vous connecter",
    "清除所有消息提示": "Effacer tous les messages",
    "扫一扫": "Balaye!",
    "消息订阅": "Abonnement aux messages",
    "绑定账户": "Lier le compte",
    "当前绑定账户": "Compte lié actuel",
    "请输入账户名": "Veuillez saisir le nom du compte",
    "密码": "Mot de passe",
    "设置密码": "Définir le mot de passe",
    "微信账户": "Compte Wechat",
    "创建平台登陆用账户": "Créer un compte pour l'ouverture de session de la plateforme",
    "新增账户绑定": "Ajouter une liaison de compte",
    "修改密码": "Modifier le mot de passe",
    "更改绑定": "Modifier la liaison",
    "清除成功": "Nettoyage réussi",
    "清除失败": "Échec de la purge",
    "登陆失败": "Échec de la connexion",
    "请输入详情": "Veuillez entrer les détails",
    "请输入标题": "Veuillez saisir un titre",
    "选择训练资源": "Sélectionner les ressources de formation",
    "答案设置": "Paramètres de réponse",
    "作业结束后查看参考答案": "Voir les réponses de référence après le travail",
    "你可以随时对参考答案进行编辑": "Vous pouvez modifier les réponses de référence à tout moment",
    "作业详情": "Détails du travail",
    "从课程资源上传": "Télécharger à partir des ressources du cours",
    "未填写": "Non rempli",
    "未设置": "Non défini",
    "请输入作业详情": "Veuillez entrer les détails de l'emploi",
    "作业编辑": "Édition des tâches",
    "请输入讨论详情": "Veuillez entrer les détails de la discussion",
    "讨论编辑": "Édition de la discussion",
    "创建新讨论": "Créer une nouvelle discussion",
    "请输入考试详情": "Veuillez entrer les détails de l'examen",
    "考试编辑": "Édition des examens",
    "创建新考试": "Créer un nouvel examen",
    "新作业": "Nouveaux emplois",
    "新讨论": "Nouvelles discussions",
    "新考试": "Nouveaux examens",
    "新发音训练作业": "Nouveaux exercices de prononciation",
    "新听写训练作业": "Nouveaux exercices de dictée",
    "新影视配音作业": "Nouveau travail de doublage vidéo",
    "保存成功": "Enregistrer avec succès",
    "创建成功": "Création réussie",
    "请在作业库中发布作业": "Publier les emplois dans la bibliothèque",
    "试试刷新吧": "Essayez de rafraîchir",
    "年": "Année",
    "周一": "Lundi",
    "周二": "Mardi",
    "周三": "Mercredi",
    "周四": "Jeudi",
    "周五": "Vendredi",
    "周六": "Samedi",
    "周日": "Dimanche",
    "刚刚": "Juste...",
    "判断题": "Questions de jugement",
    "多项选择题": "Questions à choix multiple",
    "单项选择题": "Questions à choix unique",
    "主观题": "Question subjective",
    "写作题": "Questions d'écriture",
    "抢答题": "Réponse rapide",
    "板书": "Planche",
    "未知类型": "Type inconnu",
    "收藏成功": "Collection réussie",
    "收藏失败": "La collection a échoué",
    "音轨": "Piste sonore",
    "字幕": "Sous - titres",
    "不支持视频播放": "La lecture vidéo n'est pas prise en charge",
    "音频": "Audio",
    "正在签到": "Inscription",
    "投票给": "Votez pour",
    "提交答案": "Soumettre une réponse",
    "默认分组": "Groupe par défaut",
    "人已被划分小组": "Les gens ont été divisés en groupes",
    "旋转": "Rotation",
    "使用": "Utilisation",
    "下载附件": "Télécharger les pièces jointes",
    "%s天前": "Il y a %s jours",
    "%s天后": "%s jours plus tard",
    "%s月前": "Il y a %s mois",
    "%s周前": "Il y a %s semaines",
    "%s小时前": "Il y a %s heures",
    "%s分钟前": "Il y a 1 minute (s)",
    "抢答成功,请您作答": "Réponse rapide réussie.",
    "结束后,只能查阅,不可再开始该班课,是否继续": "Une fois la classe terminée, elle ne peut être consultée que et ne peut plus être reprise.",
    "合班教学": "Enseignement en classe mixte",
    "暂不支持该语言": "La langue n'est pas prise en charge pour le moment",
    "签到结果": "Résultats de l'inscription",
    "简体中文": "Chinois simplifié",
    "英文": "Anglais",
    "日文": "Japonais",
    "韩文": "Coréen",
    "法语": "Français",
    "德语": "Allemand",
    "点击重新上传": "Cliquez pour télécharger à nouveau",
    "下载语言包": "Télécharger le paquet de langues",
    "已下载完所有语言包": "Tous les paquets de langues téléchargés",
    "下载中": "Téléchargement en cours",
    "请使用APP扫码签到": "Veuillez vous inscrire en utilisant le Code de balayage de l'application",
    "签到中": "Inscription en cours",
    "上课签到": "Inscription en classe",
    "签到历史记录": "Historique de l'inscription",
    "位置签到": "Lieu d'inscription",
    "签到开始时间": "Heure de début de l'inscription",
    "校验方式": "Méthode de vérification",
    "位置校验": "Vérification de la position",
    "%s米": "%s M",
    "您确定要开始上课吗": "Tu es sûr de vouloir commencer le cours?",
    "您确定要结束签到": "Vous êtes sûr de vouloir mettre fin à votre inscription",
    "结束中": "Fin",
    "开启中": "Ouvert",
    "校验配置": "Configuration de vérification",
    "校验距离": "Distance de contrôle",
    "请设置校验距离": "Veuillez définir la distance de contrôle",
    "当前签到已结束,无法签到": "L'inscription actuelle est terminée, l'inscription n'est pas possible",
    "签到已结束": "Inscription terminée",
    "签到状态": "État d'inscription",
    "签到方式": "Mode d'inscription",
    "您不在签到名单中": "Vous n'êtes pas sur la liste d'inscription",
    "无校验方式,无法签到": "Impossible de s'inscrire sans méthode de vérification",
    "等待教师手动设置": "Attendre la configuration manuelle de l'enseignant",
    "未到指定区域,无法签到": "Impossible de s'inscrire parce que la zone spécifiée n'est pas présente",
    "定位失败,无法签到": "Échec de la localisation, impossible de s'inscrire",
    "定位签到": "Localiser l'inscription",
    "定位超时": "Délai de localisation",
    "再试试": "Essaie encore.",
    "查看签到历史记录": "Voir l'historique d'inscription",
    "签到设置": "Paramètres d'inscription",
    "%s人": "%s personnes",
    "无记录": "Aucun enregistrement",
    "此功能只支持": "Cette fonctionnalité ne prend en charge que",
    "端中扫码使用": "Utilisation du Code de balayage du milieu de l'extrémité",
    "下载": "Télécharger",
    "开始签到": "Début de l'inscription",
    "未找到签到信息,请重新确认": "Aucune inscription trouvée, veuillez confirmer à nouveau",
    "请在": "S'il vous plaît.",
    "端中使用": "Utilisation finale",
    "定位中": "En position",
    "回调": "Rappel",
    "距离": "Distance",
    "未到指定区域": "Pas dans la zone spécifiée",
    "无法签到": "Impossible de s'inscrire",
    "学生签到": "Inscription des étudiants",
    "签到失败": "Échec de l'inscription",
    "历史记录": "Historique",
    "开启签到失败": "Échec de l'ouverture de l'inscription",
    "定位失败,无法开启签到": "Échec de la localisation, impossible d'ouvrir l'inscription",
    "教师打卡上课": "L'enseignant frappe la classe",
    "获取定位超时,休息一会吧": "Prenez un peu de repos.",
    "离开签到页面": "Quitter la page d'inscription",
    "一键设置签到": "Un bouton pour définir l'inscription",
    "设为已签到": "Set As signed",
    "设为未签到": "Set not signed",
    "一键设为已签到": "Une clé pour s'inscrire",
    "一键设为未签到": "Un bouton pour ne pas s'inscrire",
    "当前签到": "Inscription actuelle",
    "批量修改签到状态": "Modifier l'état d'inscription par lots",
    "位置更新": "Mise à jour de l'emplacement",
    "解析失败,请重新扫码": "La résolution a échoué, veuillez scanner à nouveau le Code",
    "位置更新中": "Mise à jour de l'emplacement",
    "定位失败": "Échec du positionnement",
    "扫码设置位置": "Position de réglage du balayage du Code",
    "更新位置成功": "Mise à jour réussie de l'emplacement",
    "请检测权限": "Veuillez vérifier les permissions",
    "距离%s米": "Distance %s M",
    "老师暂未开启签到": "L'enseignant n'a pas encore ouvert l'inscription",
    "你未在签到名单中,是否立刻加入": "Vous n'êtes pas sur la liste d'inscription.",
    "立刻": "Tout de suite.",
    "学生账号": "Numéro de compte de l'étudiant",
    "教师账号": "Compte de l'enseignant",
    "注册并登录": "Inscrivez - vous et connectez - vous",
    "开始签到时间": "Heure de début de l'inscription",
    "我的签到时间": "Mon heure d'inscription",
    "获取定位超时": "Obtenir le délai de localisation",
    "注册失败": "Échec de l'inscription",
    "多屏互动": "Interaction Multi - écrans",
    "直接进入": "Accès direct",
    "该功能需要登录,是否立即登录": "Cette fonction nécessite un login. Voulez - vous vous connecter maintenant?",
    "是": "- Oui.",
    "否": "Non",
    "请选择一个课程": "Veuillez sélectionner un cours",
    "统一训练": "Formation unifiée",
    "全体复位": "Réinitialisation complète",
    "全体录音": "Enregistrement complet",
    "全体回放": "Replay all",
    "语音广播": "Radiodiffusion vocale",
    "电脑声音": "Son de l'ordinateur",
    "个别通话": "Appels individuels",
    "学生发言": "Discours des étudiants",
    "我要投屏": "Je veux l'écran.",
    "我要直播": "Je veux être en direct.",
    "投屏广播": "Diffusion à l'écran",
    "屏幕广播": "Diffusion à l'écran",
    "课件库": "Bibliothèque de didacticiels",
    "小组文件": "Documents du Groupe",
    "遥控大屏": "Grand écran de télécommande",
    "对比讲解": "Comparaison des explications",
    "随机选择": "Sélection aléatoire",
    "按住发言": "Appuyez et maintenez la parole.",
    "板书快照": "Snapshot of Board Book",
    "发起训练": "Formation initiale",
    "请确认设置语系与字幕相同,否则训练功能将无法评分": "Assurez - vous que la famille linguistique est la même que le Sous - titrage, sinon la fonction de formation ne sera pas notée.",
    "统一训练结束": "Formation unifiée terminée",
    "连接中": "Connecté",
    "语音课堂互动": "Interaction phonétique en classe",
    "弹幕": "Rideau d'obus",
    "结束训练": "Fin de la formation",
    "没有更多了": "Il n'y en a plus.",
    "二维码登录": "Connexion QR",
    "请使用APP扫一扫完成登录": "Veuillez utiliser app Scan pour compléter la connexion",
    "未找到发布过的作业": "Aucun emploi publié trouvé",
    "未发布作业": "Emplois non publiés",
    "创建影视配音训练": "Créer une formation de doublage vidéo",
    "创建听写训练": "Créer une session de dictée",
    "创建发音训练": "Créer une formation à la prononciation",
    "没有库存": "Pas de stock",
    "马上创建": "Créer maintenant",
    "请发言": "Je vous donne la parole.",
    "弹幕设置": "Configuration du rideau",
    "匿名发送弹幕": "Écran d'envoi anonyme",
    "谢谢老师!": "Merci, professeur!",
    "讲得很生动": "C'était très vivant.",
    "前方高能!": "Énergie devant!",
    "匿名": "Anonyme",
    "截取板书": "Intercepter la planche",
    "有程序开启中,请稍等": "Un programme est en cours.",
    "点击发言": "Cliquez pour prendre la parole",
    "程序开启中,请稍等": "Veuillez patienter pendant que le programme est ouvert.",
    "新增组卷考试": "Nouvel examen de groupe",
    "选择试卷": "Sélectionner le document d'examen",
    "查找中": "Recherche",
    "题量": "Nombre de questions",
    "创建考试": "Créer un examen",
    "无结束作业": "Pas de fin d'emploi",
    "创建成功,请在作业库中发布": "Création réussie, veuillez publier dans la Bibliothèque de travail",
    "已交卷,等待阅卷": "Document soumis, en attente de notation",
    "出错了，试试刷新吧": "Il y a eu une erreur.",
    "ALL": "All",
    "当前设备已签到,不能再签到": "L'appareil actuel est déjà connecté et ne peut plus être connecté",
    "拒绝签到": "Refuser de signer",
    "您确定要开始训练吗": "Tu es sûr de vouloir commencer l'entraînement?",
    "确定要开始统一训练吗": "Tu es sûr de vouloir commencer l'entraînement unifié?",
    "无学员加入": "Aucun participant",
    "您确定要开始统一训练吗": "Êtes - vous sûr de vouloir commencer l'entraînement unifié",
    "结束统一训练": "Fin de la formation unifiée",
    "您确定要结束统一训练吗": "Êtes - vous sûr de vouloir terminer l'entraînement unifié",
    "匿名发送": "Envoi anonyme",
    "语音类": "Classe phonétique",
    "教学类": "Enseignement",
    "互动类": "Catégorie interactive",
    "其他": "Autres",
    "到顶了": "Au Sommet.",
    "大屏截屏": "Grande capture d'écran",
    "禁用": "Désactiver",
    "题": "Questions",
    "登录提示": "Conseils de connexion",
    "请先登录,获取更多体验权限": "Veuillez vous connecter pour plus d'expérience",
    "尚未开课": "Pas encore de cours",
    "当前不可用": "Actuellement non disponible",
    "如果未下载APP请先下载,以便获取更多体验权限": "Si l'application n'est pas téléchargée, téléchargez - la d'abord pour plus de privilèges d'expérience",
    "星期一": "Lundi",
    "星期二": "Mardi",
    "星期三": "Mercredi",
    "星期四": "Jeudi",
    "星期五": "Vendredi",
    "星期六": "Samedi",
    "星期日": "Dimanche"
}